Metadata-Version: 2.1
Name: mail-gw
Version: 0.5
Summary: Tempmail Python SDK of https://api.mail.gw/
Home-page: https://github.com/Danny-Yxzl/mail_gw
Author: Yixiangzhilv
Author-email: mail@yixiangzhilv.com
Project-URL: Bug Reports, https://github.com/Danny-Yxzl/mail_gw/issues
Project-URL: Say Thanks!, https://www.yixiangzhilv.com/
Project-URL: Source, https://github.com/Danny-Yxzl/mail_gw
Keywords: API sdk tempmail
Classifier: Intended Audience :: Developers
Classifier: License :: OSI Approved :: MIT License
Classifier: Programming Language :: Python :: 3
Classifier: Programming Language :: Python :: 3.6
Classifier: Programming Language :: Python :: 3.7
Classifier: Programming Language :: Python :: 3.8
Classifier: Programming Language :: Python :: 3.9
Classifier: Programming Language :: Python :: 3.10
License-File: LICENSE
